[[{"state":19,"x":"Trump","y":3.2916},{"state":19,"x":"Cruz","y":3.7437},{"state":19,"x":"Rubio","y":3.1277},{"state":19,"x":"Kasich","y":0.2517}],[{"state":33,"x":"Trump","y":7.2754},{"state":33,"x":"Cruz","y":2.4049},{"state":33,"x":"Rubio","y":2.1761},{"state":33,"x":"Kasich","y":3.2541}],[{"state":45,"x":"Trump","y":17.3794},{"state":45,"x":"Cruz","y":11.9406},{"state":45,"x":"Rubio","y":12.0196},{"state":45,"x":"Kasich","y":4.0727}],[{"state":32,"x":"Trump","y":2.5021},{"state":32,"x":"Cruz","y":1.1651},{"state":32,"x":"Rubio","y":1.2999},{"state":32,"x":"Kasich","y":0.1963}],[{"state":1,"x":"Trump","y":26.9357},{"state":1,"x":"Cruz","y":13.0867},{"state":1,"x":"Rubio","y":11.5791},{"state":1,"x":"Kasich","y":2.7513}],[{"state":2,"x":"Trump","y":0.5323},{"state":2,"x":"Cruz","y":0.5777},{"state":2,"x":"Rubio","y":0.2404},{"state":2,"x":"Kasich","y":0.0646}],[{"state":5,"x":"Trump","y":9.6475},{"state":5,"x":"Cruz","y":8.9758},{"state":5,"x":"Rubio","y":7.3354},{"state":5,"x":"Kasich","y":1.094}],[{"state":13,"x":"Trump","y":36.3534},{"state":13,"x":"Cruz","y":22.108},{"state":13,"x":"Rubio","y":22.8956},{"state":13,"x":"Kasich","y":5.239}],[{"state":25,"x":"Trump","y":22.5575},{"state":25,"x":"Cruz","y":4.3818},{"state":25,"x":"Rubio","y":8.175},{"state":25,"x":"Kasich","y":8.2446}],[{"state":27,"x":"Trump","y":1.7403},{"state":27,"x":"Cruz","y":2.3683},{"state":27,"x":"Rubio","y":2.98},{"state":27,"x":"Kasich","y":0.4701}],[{"state":40,"x":"Trump","y":9.4299},{"state":40,"x":"Cruz","y":11.4443},{"state":40,"x":"Rubio","y":8.6634},{"state":40,"x":"Kasich","y":1.1967}],[{"state":47,"x":"Trump","y":24.1074},{"state":47,"x":"Cruz","y":15.3004},{"state":47,"x":"Rubio","y":13.1143},{"state":47,"x":"Kasich","y":3.2783}],[{"state":48,"x":"Trump","y":54.8965},{"state":48,"x":"Cruz","y":89.8039},{"state":48,"x":"Rubio","y":36.3908},{"state":48,"x":"Kasich","y":8.7137}],[{"state":50,"x":"Trump","y":1.4469},{"state":50,"x":"Cruz","y":0.4296},{"state":50,"x":"Rubio","y":0.8534},{"state":50,"x":"Kasich","y":1.3436}],[{"state":51,"x":"Trump","y":25.7926},{"state":51,"x":"Cruz","y":12.5495},{"state":51,"x":"Rubio","y":23.6972},{"state":51,"x":"Kasich","y":6.9937}],[{"state":20,"x":"Trump","y":1.2363},{"state":20,"x":"Cruz","y":2.5511},{"state":20,"x":"Rubio","y":0.8832},{"state":20,"x":"Kasich","y":0.5648}],[{"state":21,"x":"Trump","y":5.9774},{"state":21,"x":"Cruz","y":5.2535},{"state":21,"x":"Rubio","y":2.7229},{"state":21,"x":"Kasich","y":2.4009}],[{"state":22,"x":"Trump","y":9.0442},{"state":22,"x":"Cruz","y":8.2567},{"state":22,"x":"Rubio","y":2.4494},{"state":22,"x":"Kasich","y":1.4025}],[{"state":23,"x":"Trump","y":0.4398},{"state":23,"x":"Cruz","y":0.6195},{"state":23,"x":"Rubio","y":0.1081},{"state":23,"x":"Kasich","y":0.1645}],[{"state":15,"x":"Trump","y":0.4114},{"state":15,"x":"Cruz","y":0.3173},{"state":15,"x":"Rubio","y":0.1275},{"state":15,"x":"Kasich","y":0.1024}],[{"state":16,"x":"Trump","y":4.5271},{"state":16,"x":"Cruz","y":7.3142},{"state":16,"x":"Rubio","y":2.5612},{"state":16,"x":"Kasich","y":1.1968}],[{"state":26,"x":"Trump","y":35.0523},{"state":26,"x":"Cruz","y":23.9127},{"state":26,"x":"Rubio","y":8.9613},{"state":26,"x":"Kasich","y":23.3069}],[{"state":28,"x":"Trump","y":13.8944},{"state":28,"x":"Cruz","y":10.6562},{"state":28,"x":"Rubio","y":1.5048},{"state":28,"x":"Kasich","y":2.5953}],[{"state":11,"x":"Trump","y":0.0283},{"state":11,"x":"Cruz","y":0.0254},{"state":11,"x":"Rubio","y":0.0767},{"state":11,"x":"Kasich","y":0.0731}],[{"state":12,"x":"Trump","y":78.0547},{"state":12,"x":"Cruz","y":29.2475},{"state":12,"x":"Rubio","y":46.1315},{"state":12,"x":"Kasich","y":11.5509}],[{"state":17,"x":"Trump","y":39.9289},{"state":17,"x":"Cruz","y":31.1698},{"state":17,"x":"Rubio","y":8.9092},{"state":17,"x":"Kasich","y":20.2537}],[{"state":29,"x":"Trump","y":27.6862},{"state":29,"x":"Cruz","y":27.5611},{"state":29,"x":"Rubio","y":4.1306},{"state":29,"x":"Kasich","y":6.7049}],[{"state":37,"x":"Trump","y":33.1973},{"state":37,"x":"Cruz","y":30.3416},{"state":37,"x":"Rubio","y":6.3661},{"state":37,"x":"Kasich","y":10.4558}],[{"state":39,"x":"Trump","y":52.7203},{"state":39,"x":"Cruz","y":19.3895},{"state":39,"x":"Rubio","y":4.3054},{"state":39,"x":"Kasich","y":69.3264}],[{"state":4,"x":"Trump","y":18.1088},{"state":4,"x":"Cruz","y":9.5753},{"state":4,"x":"Rubio","y":5.1124},{"state":4,"x":"Kasich","y":3.8432}],[{"state":49,"x":"Trump","y":1.8016},{"state":49,"x":"Cruz","y":8.8811},{"state":49,"x":"Rubio","y":0},{"state":49,"x":"Kasich","y":2.1573}]]
